dt_model/__init__.py
dt_model/engine/__init__.py
dt_model/engine/atomic/__init__.py
dt_model/engine/frontend/__init__.py
dt_model/engine/frontend/graph.py
dt_model/engine/frontend/linearize.py
dt_model/engine/frontend/pretty.py
dt_model/engine/numpybackend/__init__.py
dt_model/engine/numpybackend/debug.py
dt_model/engine/numpybackend/dispatch.py
dt_model/engine/numpybackend/executor.py
dt_model/ensemble/__init__.py
dt_model/internal/__init__.py
dt_model/internal/sympyke/__init__.py
dt_model/internal/sympyke/operators.py
dt_model/internal/sympyke/piecewise.py
dt_model/internal/sympyke/symbol.py
dt_model/model/__init__.py
dt_model/model/abstract_model.py
dt_model/model/instantiated_model.py
dt_model/model/legacy_model.py
dt_model/model/model.py
dt_model/simulation/__init__.py
dt_model/simulation/ensemble.py
dt_model/simulation/evaluation.py
dt_model/symbols/__init__.py
dt_model/symbols/_base.py
dt_model/symbols/constraint.py
dt_model/symbols/context_variable.py
dt_model/symbols/index.py
dt_model/symbols/presence_variable.py
fbk_dt_model-0.1.0.dist-info/licenses/LICENSE
fbk_dt_model-0.1.0.dist-info/METADATA
fbk_dt_model-0.1.0.dist-info/WHEEL
fbk_dt_model-0.1.0.dist-info/top_level.txt
fbk_dt_model-0.1.0.dist-info/RECORD
