Metadata-Version: 2.4
Name: fbk-dt-model
Version: 0.1.0
Summary: DigitalTwins Model
Author-email: Fondazione Bruno Kessler <most@fbk.eu>, Marco Pistore <pistore@fbk.eu>, Simone Basso <sibasso@fbk.eu>
License:                                  Apache License
Project-URL: Homepage, https://github.com/fbk-most/dt-model
Classifier: License :: OSI Approved :: Apache Software License
Classifier: Programming Language :: Python :: 3.11
Classifier: Programming Language :: Python :: 3.12
Classifier: Programming Language :: Python :: 3.13
Requires-Python: >=3.11.0
License-File: LICENSE
Requires-Dist: sympy>=1.13.0
Requires-Dist: numpy>=2.2.0
Requires-Dist: pandas>=2.2.0
Requires-Dist: scipy>=1.15.0
Dynamic: license-file
